route53_recordset_converter/__init__.py
route53_recordset_converter/app.py
route53_recordset_converter-0.2.4.data/scripts/route53-recordset-converter
route53_recordset_converter-0.2.4.dist-info/LICENSE
route53_recordset_converter-0.2.4.dist-info/METADATA
route53_recordset_converter-0.2.4.dist-info/WHEEL
route53_recordset_converter-0.2.4.dist-info/top_level.txt
route53_recordset_converter-0.2.4.dist-info/RECORD
