Metadata-Version: 2.1
Name: route53-recordset-converter
Version: 0.2.4
Summary: Converts an input CSV file from route53-transfer to a JSON file which can be then used in a Terraform google_dns_record_set
Home-page: http://github.com/giefferre/route53-recordset-converter
Author: Gianfranco Reppucci
Author-email: gianfranco@reppucci.it
License: Apache License 2.0
Platform: UNKNOWN
Classifier: Environment :: Console
Classifier: License :: OSI Approved :: Apache Software License
Classifier: Topic :: Utilities
Requires-Dist: docopt (==0.6.2)
